spinex_sr/__init__.py
spinex_sr/spinex.py
spinex_sr-0.1.1.dist-info/METADATA
spinex_sr-0.1.1.dist-info/WHEEL
spinex_sr-0.1.1.dist-info/top_level.txt
spinex_sr-0.1.1.dist-info/RECORD
