Metadata-Version: 2.4
Name: spinex_sr
Version: 0.1.1
Summary: Symbolic Regression with SPINEX algorithm
Home-page: https://github.com/mznaser-clemsonr
Author: M.Z. Naser
Author-email: mznaser@clemson.edu
License: MIT
Classifier: Programming Language :: Python :: 3
Classifier: Operating System :: OS Independent
Requires-Python: >=3.6
Requires-Dist: numpy>=1.19.0
Requires-Dist: sympy>=1.7.0
Requires-Dist: scikit-learn>=0.24.0
Requires-Dist: scipy>=1.6.0
Requires-Dist: joblib>=1.0.0
Requires-Dist: matplotlib>=3.3.0
Requires-Dist: termcolor>=1.1.0
Dynamic: author
Dynamic: author-email
Dynamic: classifier
Dynamic: description
Dynamic: description-content-type
Dynamic: home-page
Dynamic: license
Dynamic: requires-dist
Dynamic: requires-python
Dynamic: summary
